MANIFEST.in
README
__init__.py
__pkginfo__.py
entities.py
schema.py
setup.py
views.py
cubicweb_zone.egg-info/PKG-INFO
cubicweb_zone.egg-info/SOURCES.txt
cubicweb_zone.egg-info/dependency_links.txt
cubicweb_zone.egg-info/requires.txt
cubicweb_zone.egg-info/top_level.txt
data/icon_zone.gif
i18n/en.po
i18n/fr.po
migration/1.3.0_Any.py
migration/postcreate.py