Metadata-Version: 1.0
Name: cubicweb-zone
Version: 1.4.0
Summary: geographical zone component for the CubicWeb framework
Home-page: http://www.cubicweb.org/project/cubicweb-zone
Author: Logilab
Author-email: contact@logilab.fr
License: LGPL
Platform: UNKNOWN
